mof/__init__.py
mof/increment_version.py
mof/mof.py
mof/version.py
mof/data/clusters.tar.gz
mof/data/downloads.tsv
mof/data/trees.tar.gz
mof-0.1.2.dist-info/LICENSE
mof-0.1.2.dist-info/METADATA
mof-0.1.2.dist-info/WHEEL
mof-0.1.2.dist-info/entry_points.txt
mof-0.1.2.dist-info/top_level.txt
mof-0.1.2.dist-info/RECORD
