Metadata-Version: 2.1
Name: mof
Version: 0.1.2
Summary: mof
Home-page: https://github.com/karel-brinda/mof
Author: Karel Brinda
Author-email: karel.brinda@gmail.com
License: MIT
Platform: UNKNOWN
Classifier: Development Status :: 3 - Alpha
Classifier: Programming Language :: Python :: 3 :: Only
Classifier: License :: OSI Approved :: MIT License
Requires-Python: >=3.5, <4
Requires-Dist: ete3
Requires-Dist: six
Requires-Dist: numpy
